wonderguy/MyCore.py
wonderguy/MyUtil.py
wonderguy/Tool.py
wonderguy/WBAcceleration.py
wonderguy/WBBuggy.py
wonderguy/WBControl.py
wonderguy/WBDisplay.py
wonderguy/WBDistance.py
wonderguy/WBDriver.py
wonderguy/WBHall.py
wonderguy/WBLed.py
wonderguy/WBLightBelt.py
wonderguy/WBObserver.py
wonderguy/WBPulse.py
wonderguy/WBRfCommunication.py
wonderguy/WBRfTelecontroller.py
wonderguy/WBSignal.py
wonderguy/WBUltrasonic.py
wonderguy/WBUpload.py
wonderguy/WBits.py
wonderguy/__init__.py
wonderguy/__version__.py
wonderguy/core.py
wonderguy-1.4.3.dist-info/LICENSE
wonderguy-1.4.3.dist-info/METADATA
wonderguy-1.4.3.dist-info/WHEEL
wonderguy-1.4.3.dist-info/entry_points.txt
wonderguy-1.4.3.dist-info/top_level.txt
wonderguy-1.4.3.dist-info/RECORD
