Metadata-Version: 2.1
Name: wonderguy
Version: 1.4.3
Summary: wonderbits by mfeducation.
Home-page: https://github.com/me/myproject
Author: dottie
Author-email: daejong2014@163.com
License: MIT
Platform: UNKNOWN
Classifier: License :: OSI Approved :: MIT License
Classifier: Operating System :: OS Independent
Classifier: Programming Language :: Python :: 3
Requires-Python: >=3.0.0
Requires-Dist: requests
Requires-Dist: pyserial
Requires-Dist: Click
Requires-Dist: adafruit-ampy
